githupdate/githupdate.py
githupdate-1.0.1.dist-info/LICENSE
githupdate-1.0.1.dist-info/METADATA
githupdate-1.0.1.dist-info/WHEEL
githupdate-1.0.1.dist-info/top_level.txt
githupdate-1.0.1.dist-info/RECORD
