Metadata-Version: 2.1
Name: githupdate
Version: 1.0.1
Summary: Package to update software from a github repository
Author-email: TheEC20 <mailtheec20@gmail.com>
Project-URL: Homepage, https://github.com/ExtremeCreator20/githupdate
Project-URL: Issues, https://github.com/ExtremeCreator20/githupdate/issues
Classifier: Programming Language :: Python :: 3
Classifier: Operating System :: OS Independent
Requires-Python: >=3.13
License-File: LICENSE
Requires-Dist: requests
Requires-Dist: packaging
